nefindata/__init__.py
nefindata/__version__.py
nefindata/cost_capital/__init__.py
nefindata/cost_capital/cost_capital_downloaders.py
nefindata/dividend_yield/__init__.py
nefindata/dividend_yield/dividend_yield_downloaders.py
nefindata/illiquidity_index/__init__.py
nefindata/illiquidity_index/illiquidity_downloaders.py
nefindata/loan_fees/__init__.py
nefindata/loan_fees/loan_fees_downloaders.py
nefindata/risk_factors/__init__.py
nefindata/risk_factors/risk_factors_downloaders.py
nefindata/short_interest/__init__.py
nefindata/short_interest/short_interest_downloaders.py
nefindata-0.1.2.dist-info/LICENSE
nefindata-0.1.2.dist-info/METADATA
nefindata-0.1.2.dist-info/WHEEL
nefindata-0.1.2.dist-info/top_level.txt
nefindata-0.1.2.dist-info/RECORD
