Metadata-Version: 2.1
Name: nefindata
Version: 0.1.2
Summary: Download data from NEFIN, the Brazilian Center for Research in Financial Economics of the University of São Paulo (http://www.nefin.com.br/)
Home-page: https://github.com/fernandoramacciotti/nefindata
Author: Fernando Ramacciotti
Author-email: fernandoramacciotti@gmail.com
License: MIT
Keywords: NEFIN,financial,time series,financial market,risk factors,fama french,fama factors,Brazilian market
Platform: UNKNOWN
Classifier: Development Status :: 4 - Beta
Classifier: Intended Audience :: Developers
Classifier: Intended Audience :: Financial and Insurance Industry
Classifier: Intended Audience :: Science/Research
Classifier: Intended Audience :: Education
Classifier: Topic :: Software Development :: Build Tools
Classifier: License :: OSI Approved :: MIT License
Classifier: Programming Language :: Python :: 3
Classifier: Programming Language :: Python :: 3.4
Classifier: Programming Language :: Python :: 3.5
Classifier: Programming Language :: Python :: 3.6
Classifier: Programming Language :: Python :: 3.7
Requires-Dist: pandas (>=0.24.2)
